Metadata-Version: 1.0
Name: glossia.comparator
Version: 0.1.2
Summary: Go-Smart Simulation Architecture XML interpretation
Home-page: http://gosmart-project.eu/
Author: Phil Weir (NUMA Engineering Services Ltd.)
Author-email: phil.weir@numa.ie
License: UNKNOWN
Platform: UNKNOWN
